rtl/accumulator_mem.sv
`timescale 1ns / 1ps

module accumulator_mem #(
    parameter bit BYPASS_READ_NEW = 1'b1 // 1: output newly written value same cycle
) (
    input  logic        clk,
    input  logic        reset,

    input  logic        enable, // valid data
    input  logic        accumulator_mode, // 0/1 overwrite/add
    input  logic        buffer_select, // double buffer selection

    input  logic [15:0] in_col0,
    input  logic [15:0] in_col1,

    output logic        valid_out,
    output logic signed [31:0] out_col0,
    output logic signed [31:0] out_col1
);

    // 2 x 2 x 32 bits
    logic signed [31:0] mem_buff0_col0;
    logic signed [31:0] mem_buff0_col1;
    logic signed [31:0] mem_buff1_col0;
    logic signed [31:0] mem_buff1_col1;

    always_ff @(posedge clk or posedge reset) begin
        if (reset) begin
            valid_out <= 1'b0;
            out_col0 <= 32'sd0;
            out_col1 <= 32'sd0;
            mem_buff0_col0 <= 32'sd0;
            mem_buff0_col1 <= 32'sd0;
            mem_buff1_col0 <= 32'sd0;
            mem_buff1_col1 <= 32'sd0;
        end
        else begin
            if (enable) begin
                unique case (buffer_select)
                    1'b0: begin // --- BUFFER 0 ---
                        if (accumulator_mode) begin
                            mem_buff0_col0 <= mem_buff0_col0 + $signed({16'b0, in_col0});
                            mem_buff0_col1 <= mem_buff0_col1 + $signed({16'b0, in_col1});
                        end else begin
                            mem_buff0_col0 <= $signed({16'b0, in_col0});
                            mem_buff0_col1 <= $signed({16'b0, in_col1});
                        end
                        if (BYPASS_READ_NEW) begin
                            out_col0 <= accumulator_mode ? (mem_buff0_col0 + $signed({16'b0, in_col0})) : $signed({16'b0, in_col0});
                            out_col1 <= accumulator_mode ? (mem_buff0_col1 + $signed({16'b0, in_col1})) : $signed({16'b0, in_col1});
                        end else begin
                            out_col0 <= mem_buff0_col0;
                            out_col1 <= mem_buff0_col1;
                        end
                    end

                    1'b1: begin // --- BUFFER 1 ---
                        if (accumulator_mode) begin
                            mem_buff1_col0 <= mem_buff1_col0 + $signed({16'b0, in_col0});
                            mem_buff1_col1 <= mem_buff1_col1 + $signed({16'b0, in_col1});
                        end else begin
                            mem_buff1_col0 <= $signed({16'b0, in_col0});
                            mem_buff1_col1 <= $signed({16'b0, in_col1});
                        end
                        if (BYPASS_READ_NEW) begin
                            out_col0 <= accumulator_mode ? (mem_buff1_col0 + $signed({16'b0, in_col0})) : $signed({16'b0, in_col0});
                            out_col1 <= accumulator_mode ? (mem_buff1_col1 + $signed({16'b0, in_col1})) : $signed({16'b0, in_col1});
                        end else begin
                            out_col0 <= mem_buff1_col0;
                            out_col1 <= mem_buff1_col1;
                        end
                    end
                endcase
                valid_out <= 1'b1;
            end
            else begin
                valid_out <= 1'b0;
            end
        end
    end

endmodule

rtl/accumulator_align.sv
`timescale 1ns / 1ps

module accumulator_align (
    input  logic        clk,
    input  logic        reset,

    input  logic        valid_in,
    input  logic [15:0] raw_col0,
    input  logic [15:0] raw_col1,

    output logic        aligned_valid,
    output logic [15:0] align_col0,
    output logic [15:0] align_col1
);

    // Column 0 delay register to align with column 1 (which arrives 1 cycle later
    // for the same result row due to horizontal activation propagation in systolic array)
    logic [15:0] col0_delay_reg;
    logic pending;  // True after first capture, enables output on subsequent valids

    always_ff @(posedge clk or posedge reset) begin
        if (reset) begin
            col0_delay_reg <= 16'd0;
            pending <= 1'b0;
            aligned_valid <= 1'b0;
            align_col0 <= 16'd0;
            align_col1 <= 16'd0;
        end
        else begin
            aligned_valid <= 1'b0;

            if (valid_in) begin
                if (!pending) begin
                    // First valid: capture col0 for pairing with next cycle's col1
                    col0_delay_reg <= raw_col0;
                    pending <= 1'b1;
                end else begin
                    // Subsequent valids: output aligned pair AND capture new col0
                    aligned_valid <= 1'b1;
                    align_col0 <= col0_delay_reg;  // Previous cycle's col0
                    align_col1 <= raw_col1;         // Current cycle's col1
                    col0_delay_reg <= raw_col0;     // Capture current col0 for next pair
                    // pending stays 1 for continuous streaming
                end
            end else begin
                // No valid input - reset pending for next batch
                pending <= 1'b0;
            end
        end
    end

endmodule

rtl/accumulator.sv
`timescale 1ns / 1ps

module accumulator (
    input  logic        clk,
    input  logic        reset,
    input  logic        valid_in,  // MMU data valid
    input  logic        accumulator_enable, // add to existing sum or overwrite (1/0)
    input  logic        addr_sel, // buffer selection (buffer 1, or buffer 2)

    input  logic [15:0] mmu_col0_in,
    input  logic [15:0] mmu_col1_in,

    output logic signed [31:0] acc_col0_out,
    output logic signed [31:0] acc_col1_out,
    output logic        valid_out
);

    logic        aligned_valid;
    logic [15:0] aligned_c0;
    logic [15:0] aligned_c1;

    accumulator_align u_align (
        .clk(clk),
        .reset(reset),
        .valid_in(valid_in),
        .raw_col0(mmu_col0_in),
        .raw_col1(mmu_col1_in),
        .aligned_valid(aligned_valid),
        .align_col0(aligned_c0),
        .align_col1(aligned_c1)
    );

    accumulator_mem u_mem (
        .clk(clk),
        .reset(reset),
        .enable(aligned_valid),
        .accumulator_mode(accumulator_enable),
        .buffer_select(addr_sel),
        .in_col0(aligned_c0),
        .in_col1(aligned_c1),
        .valid_out(valid_out),
        .out_col0(acc_col0_out),
        .out_col1(acc_col1_out)
    );

endmodule

sim/waves/accumulator.vcd
$version Generated by VerilatedVcd $end
$timescale 1ps $end
 $scope module $rootio $end
  $var wire 1 # clk $end
  $var wire 1 $ reset $end
  $var wire 1 % valid_in $end
  $var wire 1 & accumulator_enable $end
  $var wire 1 ' addr_sel $end
  $var wire 16 ( mmu_col0_in [15:0] $end
  $var wire 16 ) mmu_col1_in [15:0] $end
  $var wire 32 * acc_col0_out [31:0] $end
  $var wire 32 + acc_col1_out [31:0] $end
  $var wire 1 , valid_out $end
 $upscope $end
 $scope module accumulator $end
  $var wire 1 - clk $end
  $var wire 1 . reset $end
  $var wire 1 / valid_in $end
  $var wire 1 0 accumulator_enable $end
  $var wire 1 1 addr_sel $end
  $var wire 16 2 mmu_col0_in [15:0] $end
  $var wire 16 3 mmu_col1_in [15:0] $end
  $var wire 32 4 acc_col0_out [31:0] $end
  $var wire 32 5 acc_col1_out [31:0] $end
  $var wire 1 6 valid_out $end
  $var wire 1 7 aligned_valid $end
  $var wire 16 8 aligned_c0 [15:0] $end
  $var wire 16 9 aligned_c1 [15:0] $end
  $scope module u_align $end
   $var wire 1 : clk $end
   $var wire 1 ; reset $end
   $var wire 1 < valid_in $end
   $var wire 16 = raw_col0 [15:0] $end
   $var wire 16 > raw_col1 [15:0] $end
   $var wire 1 ? aligned_valid $end
   $var wire 16 @ align_col0 [15:0] $end
   $var wire 16 A align_col1 [15:0] $end
   $var wire 16 B col0_delay_reg [15:0] $end
   $var wire 1 C pending $end
  $upscope $end
  $scope module u_mem $end
   $var wire 1 R BYPASS_READ_NEW $end
   $var wire 1 D clk $end
   $var wire 1 E reset $end
   $var wire 1 F enable $end
   $var wire 1 G accumulator_mode $end
   $var wire 1 H buffer_select $end
   $var wire 16 I in_col0 [15:0] $end
   $var wire 16 J in_col1 [15:0] $end
   $var wire 1 K valid_out $end
   $var wire 32 L out_col0 [31:0] $end
   $var wire 32 M out_col1 [31:0] $end
   $var wire 32 N mem_buff0_col0 [31:0] $end
   $var wire 32 O mem_buff0_col1 [31:0] $end
   $var wire 32 P mem_buff1_col0 [31:0] $end
   $var wire 32 Q mem_buff1_col1 [31:0] $end
  $upscope $end
 $upscope $end
$enddefinitions $end


#0
1#
1$
0%
0&
0'
b0000000000000000 (
b0000000000000000 )
b00000000000000000000000000000000 *
b00000000000000000000000000000000 +
0,
1-
1.
0/
00
01
b0000000000000000 2
b0000000000000000 3
b00000000000000000000000000000000 4
b00000000000000000000000000000000 5
06
07
b0000000000000000 8
b0000000000000000 9
1:
1;
0<
b0000000000000000 =
b0000000000000000 >
0?
b0000000000000000 @
b0000000000000000 A
b0000000000000000 B
0C
1D
1E
0F
0G
0H
b0000000000000000 I
b0000000000000000 J
0K
b00000000000000000000000000000000 L
b00000000000000000000000000000000 M
b00000000000000000000000000000000 N
b00000000000000000000000000000000 O
b00000000000000000000000000000000 P
b00000000000000000000000000000000 Q
1R
#5000
0#
0-
0:
0D
#10000
1#
1-
1:
1D
#15001
0#
0-
0:
0D
#20001
1#
1-
1:
1D
#25001
0#
0-
0:
0D
#30001
1#
0$
1-
0.
1:
0;
1D
0E
#35001
0#
0-
0:
0D
#40001
1#
1%
b0000000001100100 (
b0000000011001000 )
1-
1/
b0000000001100100 2
b0000000011001000 3
1:
1<
b0000000001100100 =
b0000000011001000 >
1D
#45001
0#
0-
0:
0D
#50001
1#
b0000000010010110 (
b0000000011111010 )
1-
b0000000010010110 2
b0000000011111010 3
1:
b0000000010010110 =
b0000000011111010 >
b0000000001100100 B
1C
1D
#55001
0#
0-
0:
0D
#60001
1#
0%
1-
0/
17
b0000000001100100 8
b0000000011111010 9
1:
0<
1?
b0000000001100100 @
b0000000011111010 A
b0000000010010110 B
1D
1F
b0000000001100100 I
b0000000011111010 J
#65001
0#
0-
0:
0D
#70001
1#
b00000000000000000000000001100100 *
b00000000000000000000000011111010 +
1,
1-
b00000000000000000000000001100100 4
b00000000000000000000000011111010 5
16
07
1:
0?
0C
1D
0F
1K
b00000000000000000000000001100100 L
b00000000000000000000000011111010 M
b00000000000000000000000001100100 N
b00000000000000000000000011111010 O
#75001
0#
0-
0:
0D
#80001
1#
0,
1-
06
1:
1D
0K
#80002
1$
b00000000000000000000000000000000 *
b00000000000000000000000000000000 +
1.
b00000000000000000000000000000000 4
b00000000000000000000000000000000 5
b0000000000000000 8
b0000000000000000 9
1;
b0000000000000000 @
b0000000000000000 A
b0000000000000000 B
1E
b0000000000000000 I
b0000000000000000 J
b00000000000000000000000000000000 L
b00000000000000000000000000000000 M
b00000000000000000000000000000000 N
b00000000000000000000000000000000 O
#85002
0#
0-
0:
0D
#90002
1#
1-
1:
1D
#95002
0#
0-
0:
0D
#100002
1#
0$
1-
0.
1:
0;
1D
0E
#105002
0#
0-
0:
0D
#110002
1#
b0000000000000000 (
b0000000000000000 )
1-
b0000000000000000 2
b0000000000000000 3
1:
b0000000000000000 =
b0000000000000000 >
1D
#115002
0#
0-
0:
0D
#120002
1#
1%
b0000000000001010 (
b0000000000010100 )
1-
1/
b0000000000001010 2
b0000000000010100 3
1:
1<
b0000000000001010 =
b0000000000010100 >
1D
#125002
0#
0-
0:
0D
#130002
1#
b0000000000001111 (
b0000000000011001 )
1-
b0000000000001111 2
b0000000000011001 3
1:
b0000000000001111 =
b0000000000011001 >
b0000000000001010 B
1C
1D
#135002
0#
0-
0:
0D
#140002
1#
0%
1-
0/
17
b0000000000001010 8
b0000000000011001 9
1:
0<
1?
b0000000000001010 @
b0000000000011001 A
b0000000000001111 B
1D
1F
b0000000000001010 I
b0000000000011001 J
#145002
0#
0-
0:
0D
#150002
1#
b00000000000000000000000000001010 *
b00000000000000000000000000011001 +
1,
1-
b00000000000000000000000000001010 4
b00000000000000000000000000011001 5
16
07
1:
0?
0C
1D
0F
1K
b00000000000000000000000000001010 L
b00000000000000000000000000011001 M
b00000000000000000000000000001010 N
b00000000000000000000000000011001 O
#155002
0#
0-
0:
0D
#160002
1#
1%
1&
b0000000000000101 (
b0000000000001010 )
0,
1-
1/
10
b0000000000000101 2
b0000000000001010 3
06
1:
1<
b0000000000000101 =
b0000000000001010 >
1D
1G
0K
#165002
0#
0-
0:
0D
#170002
1#
b0000000000000111 (
b0000000000001100 )
1-
b0000000000000111 2
b0000000000001100 3
1:
b0000000000000111 =
b0000000000001100 >
b0000000000000101 B
1C
1D
#175002
0#
0-
0:
0D
#180002
1#
0%
1-
0/
17
b0000000000000101 8
b0000000000001100 9
1:
0<
1?
b0000000000000101 @
b0000000000001100 A
b0000000000000111 B
1D
1F
b0000000000000101 I
b0000000000001100 J
#185002
0#
0-
0:
0D
#190002
1#
b00000000000000000000000000001111 *
b00000000000000000000000000100101 +
1,
1-
b00000000000000000000000000001111 4
b00000000000000000000000000100101 5
16
07
1:
0?
0C
1D
0F
1K
b00000000000000000000000000001111 L
b00000000000000000000000000100101 M
b00000000000000000000000000001111 N
b00000000000000000000000000100101 O
#195002
0#
0-
0:
0D
#200002
1#
0,
1-
06
1:
1D
0K
#200003
1$
b00000000000000000000000000000000 *
b00000000000000000000000000000000 +
1.
b00000000000000000000000000000000 4
b00000000000000000000000000000000 5
b0000000000000000 8
b0000000000000000 9
1;
b0000000000000000 @
b0000000000000000 A
b0000000000000000 B
1E
b0000000000000000 I
b0000000000000000 J
b00000000000000000000000000000000 L
b00000000000000000000000000000000 M
b00000000000000000000000000000000 N
b00000000000000000000000000000000 O
#205003
0#
0-
0:
0D
#210003
1#
1-
1:
1D
#215003
0#
0-
0:
0D
#220003
1#
0$
1-
0.
1:
0;
1D
0E
#225003
0#
0-
0:
0D
#230003
1#
0&
b0000000000000000 (
b0000000000000000 )
1-
00
b0000000000000000 2
b0000000000000000 3
1:
b0000000000000000 =
b0000000000000000 >
1D
0G
#235003
0#
0-
0:
0D
#240003
1#
1%
b0000000001101111 (
b0000000011011110 )
1-
1/
b0000000001101111 2
b0000000011011110 3
1:
1<
b0000000001101111 =
b0000000011011110 >
1D
#245003
0#
0-
0:
0D
#250003
1#
b0000000101001101 (
b0000000110111100 )
1-
b0000000101001101 2
b0000000110111100 3
1:
b0000000101001101 =
b0000000110111100 >
b0000000001101111 B
1C
1D
#255003
0#
0-
0:
0D
#260003
1#
0%
1-
0/
17
b0000000001101111 8
b0000000110111100 9
1:
0<
1?
b0000000001101111 @
b0000000110111100 A
b0000000101001101 B
1D
1F
b0000000001101111 I
b0000000110111100 J
#265003
0#
0-
0:
0D
#270003
1#
b00000000000000000000000001101111 *
b00000000000000000000000110111100 +
1,
1-
b00000000000000000000000001101111 4
b00000000000000000000000110111100 5
16
07
1:
0?
0C
1D
0F
1K
b00000000000000000000000001101111 L
b00000000000000000000000110111100 M
b00000000000000000000000001101111 N
b00000000000000000000000110111100 O
#275003
0#
0-
0:
0D
#280003
1#
1%
1'
b0000001000101011 (
b0000001010011010 )
0,
1-
1/
11
b0000001000101011 2
b0000001010011010 3
06
1:
1<
b0000001000101011 =
b0000001010011010 >
1D
1H
0K
#285003
0#
0-
0:
0D
#290003
1#
b0000001100001001 (
b0000001101111000 )
1-
b0000001100001001 2
b0000001101111000 3
1:
b0000001100001001 =
b0000001101111000 >
b0000001000101011 B
1C
1D
#295003
0#
0-
0:
0D
#300003
1#
0%
1-
0/
17
b0000001000101011 8
b0000001101111000 9
1:
0<
1?
b0000001000101011 @
b0000001101111000 A
b0000001100001001 B
1D
1F
b0000001000101011 I
b0000001101111000 J
#305003
0#
0-
0:
0D
#310003
1#
b00000000000000000000001000101011 *
b00000000000000000000001101111000 +
1,
1-
b00000000000000000000001000101011 4
b00000000000000000000001101111000 5
16
07
1:
0?
0C
1D
0F
1K
b00000000000000000000001000101011 L
b00000000000000000000001101111000 M
b00000000000000000000001000101011 P
b00000000000000000000001101111000 Q
#315003
0#
0-
0:
0D
#320003
1#
0,
1-
06
1:
1D
0K
#320004
1$
b00000000000000000000000000000000 *
b00000000000000000000000000000000 +
1.
b00000000000000000000000000000000 4
b00000000000000000000000000000000 5
b0000000000000000 8
b0000000000000000 9
1;
b0000000000000000 @
b0000000000000000 A
b0000000000000000 B
1E
b0000000000000000 I
b0000000000000000 J
b00000000000000000000000000000000 L
b00000000000000000000000000000000 M
b00000000000000000000000000000000 N
b00000000000000000000000000000000 O
b00000000000000000000000000000000 P
b00000000000000000000000000000000 Q
#325004
0#
0-
0:
0D
#330004
1#
1-
1:
1D
#335004
0#
0-
0:
0D
#340004
1#
0$
1-
0.
1:
0;
1D
0E
#345004
0#
0-
0:
0D
#350004
1#
0'
1-
01
1:
1D
0H
#355004
0#
0-
0:
0D
#360004
1#
1%
b0000000001100100 (
b0000001111100111 )
1-
1/
b0000000001100100 2
b0000001111100111 3
1:
1<
b0000000001100100 =
b0000001111100111 >
1D
#365004
0#
0-
0:
0D
#370004
1#
b0000000011001000 (
b0000000001100100 )
1-
b0000000011001000 2
b0000000001100100 3
1:
b0000000011001000 =
b0000000001100100 >
b0000000001100100 B
1C
1D
#375004
0#
0-
0:
0D
#380004
1#
0%
1-
0/
17
b0000000001100100 8
b0000000001100100 9
1:
0<
1?
b0000000001100100 @
b0000000001100100 A
b0000000011001000 B
1D
1F
b0000000001100100 I
b0000000001100100 J
#385004
0#
0-
0:
0D
#390004
1#
b00000000000000000000000001100100 *
b00000000000000000000000001100100 +
1,
1-
b00000000000000000000000001100100 4
b00000000000000000000000001100100 5
16
07
1:
0?
0C
1D
0F
1K
b00000000000000000000000001100100 L
b00000000000000000000000001100100 M
b00000000000000000000000001100100 N
b00000000000000000000000001100100 O
#395004
0#
0-
0:
0D
#400004
1#
0,
1-
06
1:
1D
0K
