rtl/loss_block.sv
`timescale 1ns / 1ps

// Computes per-element L1 loss: |data_in - target_in|
module loss_block (
    input  logic        clk,
    input  logic        reset,
    input  logic        valid_in,
    input  logic signed [31:0] data_in,
    input  logic signed [31:0] target_in,
    output logic        valid_out,
    output logic signed [31:0] loss_out
);

    logic signed [31:0] diff;
    logic signed [31:0] abs_diff;

    assign diff = data_in - target_in;
    assign abs_diff = diff[31] ? -diff : diff;

    always_ff @(posedge clk or posedge reset) begin
        if (reset) begin
            valid_out <= 1'b0;
            loss_out  <= 32'sd0;
        end else begin
            valid_out <= valid_in;
            loss_out  <= abs_diff;
        end
    end

endmodule

rtl/normalizer.sv
`timescale 1ns / 1ps

// Fixed-point normalization: (data_in * gain) >> shift + bias
// gain is signed Qm.n; shift controls right shift to rescale.
module normalizer (
    input  logic        clk,
    input  logic        reset,
    input  logic        valid_in,
    input  logic signed [31:0] data_in,
    input  logic signed [15:0] gain,
    input  logic signed [31:0] bias,
    input  logic [4:0]  shift,
    output logic        valid_out,
    output logic signed [31:0] data_out
);

    // Wider product to hold intermediate result
    logic signed [47:0] mult;
    logic signed [47:0] shifted;

    assign mult = data_in * gain;
    assign shifted = mult >>> shift;

    always_ff @(posedge clk or posedge reset) begin
        if (reset) begin
            valid_out <= 1'b0;
            data_out  <= 32'sd0;
        end else begin
            valid_out <= valid_in;
            data_out  <= shifted[31:0] + bias;
        end
    end

endmodule

rtl/activation_func.sv
`timescale 1ns / 1ps

// Simple activation block with selectable function.
// DEFAULT_ACT: 00=passthrough, 01=ReLU, 10=ReLU6 (clamps to 6)
module activation_func #(
    parameter logic [1:0] DEFAULT_ACT = 2'b01
) (
    input  logic        clk,
    input  logic        reset,
    input  logic        valid_in,
    input  logic signed [31:0] data_in,
    output logic        valid_out,
    output logic signed [31:0] data_out
);

    always_ff @(posedge clk or posedge reset) begin
        if (reset) begin
            valid_out <= 1'b0;
            data_out  <= 32'sd0;
        end else begin
            valid_out <= valid_in;
            unique case (DEFAULT_ACT)
                2'b00: data_out <= data_in;                          // passthrough
                2'b01: data_out <= data_in[31] ? 32'sd0 : data_in;   // ReLU
                2'b10: begin                                         // ReLU6 (clamp to 6)
                    if (data_in[31])
                        data_out <= 32'sd0;
                    else if (data_in > 32'sd6)
                        data_out <= 32'sd6;
                    else
                        data_out <= data_in;
                end
                default: data_out <= data_in;
            endcase
        end
    end

endmodule

rtl/activation_pipeline.sv
`timescale 1ns / 1ps

// Top-level activation pipeline: Accumulator -> Activation -> Normalization -> Loss -> Quantize -> Unified Buffer input
module activation_pipeline (
    input  logic        clk,
    input  logic        reset,
    input  logic        valid_in,
    input  logic signed [31:0] acc_in,       // from accumulator
    input  logic signed [31:0] target_in,    // optional target for loss (set to 0 if unused)

    // Configuration
    input  logic signed [15:0] norm_gain,
    input  logic signed [31:0] norm_bias,
    input  logic [4:0]  norm_shift,
    input  logic signed [15:0] q_inv_scale, // 1/S in Q8.8
    input  logic signed [7:0] q_zero_point,

    // Outputs
    output logic        valid_out,
    output logic signed [7:0] ub_data_out,   // to unified buffer
    output logic        loss_valid,
    output logic signed [31:0] loss_out
);

    // Stage 1: Activation
    logic        s1_valid;
    logic signed [31:0] s1_data;
    logic signed [31:0] target_d1;

    activation_func act_u (
        .clk(clk),
        .reset(reset),
        .valid_in(valid_in),
        .data_in(acc_in),
        .valid_out(s1_valid),
        .data_out(s1_data)
    );

    // Align target with pipeline (normalizer adds one cycle)
    always_ff @(posedge clk or posedge reset) begin
        if (reset)
            target_d1 <= 32'sd0;
        else if (valid_in)
            target_d1 <= target_in;
    end

    // Stage 2: Normalization
    logic        s2_valid;
    logic signed [31:0] s2_data;

    normalizer norm_u (
        .clk(clk),
        .reset(reset),
        .valid_in(s1_valid),
        .data_in(s1_data),
        .gain(norm_gain),
        .bias(norm_bias),
        .shift(norm_shift),
        .valid_out(s2_valid),
        .data_out(s2_data)
    );

    // Stage 3a: Loss (in parallel with quantization)
    loss_block loss_u (
        .clk(clk),
        .reset(reset),
        .valid_in(s2_valid),
        .data_in(s2_data),
        .target_in(target_d1),
        .valid_out(loss_valid),
        .loss_out(loss_out)
    );

    // Stage 3b: Quantization to UB (inlined affine quantization)
    // x_q = clip( round(x * (1/S)) + Z , -128, 127 )
    logic signed [7:0] ub_q_reg;
    logic valid_reg;

    logic signed [47:0] mult;
    logic signed [47:0] mult_rounded;
    logic signed [31:0] scaled;
    logic signed [31:0] biased;

    assign mult = s2_data * q_inv_scale;              // 32x16 -> 48
    assign mult_rounded = mult + 48'sd128;            // +0.5 * 2^8 for nearest
    assign scaled = 32'(mult_rounded >>> 8);          // back to Q0
    assign biased = scaled + {{24{q_zero_point[7]}}, q_zero_point};

    // Saturation function
    function automatic logic signed [7:0] sat_int8(input logic signed [31:0] val);
        if (val > 32'sd127)
            return 8'sd127;
        else if (val < -32'sd128)
            return -8'sd128;
        else
            return val[7:0];
    endfunction

    always_ff @(posedge clk or posedge reset) begin
        if (reset) begin
            valid_reg <= 1'b0;
            ub_q_reg  <= 8'sd0;
        end else begin
            valid_reg <= s2_valid;
            ub_q_reg  <= sat_int8(biased);
        end
    end

    assign valid_out   = valid_reg;
    assign ub_data_out = ub_q_reg;

endmodule

sim/waves/activation_pipeline.vcd
$version Generated by VerilatedVcd $end
$timescale 1ps $end
 $scope module $rootio $end
  $var wire 1 # clk $end
  $var wire 1 $ reset $end
  $var wire 1 % valid_in $end
  $var wire 32 & acc_in [31:0] $end
  $var wire 32 ' target_in [31:0] $end
  $var wire 16 ( norm_gain [15:0] $end
  $var wire 32 ) norm_bias [31:0] $end
  $var wire 5 * norm_shift [4:0] $end
  $var wire 16 + q_inv_scale [15:0] $end
  $var wire 8 , q_zero_point [7:0] $end
  $var wire 1 - valid_out $end
  $var wire 8 . ub_data_out [7:0] $end
  $var wire 1 / loss_valid $end
  $var wire 32 0 loss_out [31:0] $end
 $upscope $end
 $scope module activation_pipeline $end
  $var wire 1 1 clk $end
  $var wire 1 2 reset $end
  $var wire 1 3 valid_in $end
  $var wire 32 4 acc_in [31:0] $end
  $var wire 32 5 target_in [31:0] $end
  $var wire 16 6 norm_gain [15:0] $end
  $var wire 32 7 norm_bias [31:0] $end
  $var wire 5 8 norm_shift [4:0] $end
  $var wire 16 9 q_inv_scale [15:0] $end
  $var wire 8 : q_zero_point [7:0] $end
  $var wire 1 ; valid_out $end
  $var wire 8 < ub_data_out [7:0] $end
  $var wire 1 = loss_valid $end
  $var wire 32 > loss_out [31:0] $end
  $var wire 1 ? s1_valid $end
  $var wire 32 @ s1_data [31:0] $end
  $var wire 32 A target_d1 [31:0] $end
  $var wire 1 B s2_valid $end
  $var wire 32 C s2_data [31:0] $end
  $var wire 8 D ub_q_reg [7:0] $end
  $var wire 1 E valid_reg $end
  $var wire 48 F mult [47:0] $end
  $var wire 48 H mult_rounded [47:0] $end
  $var wire 32 J scaled [31:0] $end
  $var wire 32 K biased [31:0] $end
  $scope module act_u $end
   $var wire 2 h DEFAULT_ACT [1:0] $end
   $var wire 1 L clk $end
   $var wire 1 M reset $end
   $var wire 1 N valid_in $end
   $var wire 32 O data_in [31:0] $end
   $var wire 1 P valid_out $end
   $var wire 32 Q data_out [31:0] $end
  $upscope $end
  $scope module loss_u $end
   $var wire 1 R clk $end
   $var wire 1 S reset $end
   $var wire 1 T valid_in $end
   $var wire 32 U data_in [31:0] $end
   $var wire 32 V target_in [31:0] $end
   $var wire 1 W valid_out $end
   $var wire 32 X loss_out [31:0] $end
   $var wire 32 Y diff [31:0] $end
   $var wire 32 Z abs_diff [31:0] $end
  $upscope $end
  $scope module norm_u $end
   $var wire 1 [ clk $end
   $var wire 1 \ reset $end
   $var wire 1 ] valid_in $end
   $var wire 32 ^ data_in [31:0] $end
   $var wire 16 _ gain [15:0] $end
   $var wire 32 ` bias [31:0] $end
   $var wire 5 a shift [4:0] $end
   $var wire 1 b valid_out $end
   $var wire 32 c data_out [31:0] $end
   $var wire 48 d mult [47:0] $end
   $var wire 48 f shifted [47:0] $end
  $upscope $end
 $upscope $end
$enddefinitions $end


#0
1#
1$
0%
b00000000000000000000000000000000 &
b00000000000000000000000000000000 '
b0000000100000000 (
b00000000000000000000000000000000 )
b01000 *
b0000000100000000 +
b00000000 ,
0-
b00000000 .
0/
b00000000000000000000000000000000 0
11
12
03
b00000000000000000000000000000000 4
b00000000000000000000000000000000 5
b0000000100000000 6
b00000000000000000000000000000000 7
b01000 8
b0000000100000000 9
b00000000 :
0;
b00000000 <
0=
b00000000000000000000000000000000 >
0?
b00000000000000000000000000000000 @
b00000000000000000000000000000000 A
0B
b00000000000000000000000000000000 C
b00000000 D
0E
b000000000000000000000000000000000000000000000000 F
b000000000000000000000000000000000000000010000000 H
b00000000000000000000000000000000 J
b00000000000000000000000000000000 K
1L
1M
0N
b00000000000000000000000000000000 O
0P
b00000000000000000000000000000000 Q
1R
1S
0T
b00000000000000000000000000000000 U
b00000000000000000000000000000000 V
0W
b00000000000000000000000000000000 X
b00000000000000000000000000000000 Y
b00000000000000000000000000000000 Z
1[
1\
0]
b00000000000000000000000000000000 ^
b0000000100000000 _
b00000000000000000000000000000000 `
b01000 a
0b
b00000000000000000000000000000000 c
b000000000000000000000000000000000000000000000000 d
b000000000000000000000000000000000000000000000000 f
b01 h
#5000
0#
01
0L
0R
0[
#10000
1#
11
1L
1R
1[
#15001
0#
01
0L
0R
0[
#20001
1#
11
1L
1R
1[
#25001
0#
01
0L
0R
0[
#30001
1#
0$
11
02
1L
0M
1R
0S
1[
0\
#35001
0#
01
0L
0R
0[
#40001
1#
1%
b00000000000000000000000000101010 &
11
13
b00000000000000000000000000101010 4
1L
1N
b00000000000000000000000000101010 O
1R
1[
#45001
0#
01
0L
0R
0[
#50001
1#
0%
11
03
1?
b00000000000000000000000000101010 @
1L
0N
1P
b00000000000000000000000000101010 Q
1R
1[
1]
b00000000000000000000000000101010 ^
b000000000000000000000000000000000010101000000000 d
b000000000000000000000000000000000000000000101010 f
#55001
0#
01
0L
0R
0[
#60001
1#
11
0?
1B
b00000000000000000000000000101010 C
b000000000000000000000000000000000010101000000000 F
b000000000000000000000000000000000010101010000000 H
b00000000000000000000000000101010 J
b00000000000000000000000000101010 K
1L
0P
1R
1T
b00000000000000000000000000101010 U
b00000000000000000000000000101010 Y
b00000000000000000000000000101010 Z
1[
0]
1b
b00000000000000000000000000101010 c
#65001
0#
01
0L
0R
0[
#70001
1#
1-
b00101010 .
1/
b00000000000000000000000000101010 0
11
1;
b00101010 <
1=
b00000000000000000000000000101010 >
0B
b00101010 D
1E
1L
1R
0T
1W
b00000000000000000000000000101010 X
1[
0b
#75001
0#
01
0L
0R
0[
#80001
1#
0-
0/
11
0;
0=
0E
1L
1R
0W
1[
#85001
0#
01
0L
0R
0[
#90001
1#
11
1L
1R
1[
#95001
0#
01
0L
0R
0[
#100001
1#
11
1L
1R
1[
#100002
1$
b00000000 .
b00000000000000000000000000000000 0
12
b00000000 <
b00000000000000000000000000000000 >
b00000000000000000000000000000000 @
b00000000000000000000000000000000 C
b00000000 D
b000000000000000000000000000000000000000000000000 F
b000000000000000000000000000000000000000010000000 H
b00000000000000000000000000000000 J
b00000000000000000000000000000000 K
1M
b00000000000000000000000000000000 Q
1S
b00000000000000000000000000000000 U
b00000000000000000000000000000000 X
b00000000000000000000000000000000 Y
b00000000000000000000000000000000 Z
1\
b00000000000000000000000000000000 ^
b00000000000000000000000000000000 c
b000000000000000000000000000000000000000000000000 d
b000000000000000000000000000000000000000000000000 f
#105002
0#
01
0L
0R
0[
#110002
1#
11
1L
1R
1[
#115002
0#
01
0L
0R
0[
#120002
1#
0$
11
02
1L
0M
1R
0S
1[
0\
#125002
0#
01
0L
0R
0[
#130002
1#
1%
b11111111111111111111111111001110 &
11
13
b11111111111111111111111111001110 4
b00000000000000000000000000101010 @
1L
1N
b11111111111111111111111111001110 O
b00000000000000000000000000101010 Q
1R
1[
b00000000000000000000000000101010 ^
b000000000000000000000000000000000010101000000000 d
b000000000000000000000000000000000000000000101010 f
#135002
0#
01
0L
0R
0[
#140002
1#
0%
11
03
1?
b00000000000000000000000000000000 @
b00000000000000000000000000101010 C
b000000000000000000000000000000000010101000000000 F
b000000000000000000000000000000000010101010000000 H
b00000000000000000000000000101010 J
b00000000000000000000000000101010 K
1L
0N
1P
b00000000000000000000000000000000 Q
1R
b00000000000000000000000000101010 U
b00000000000000000000000000101010 Y
b00000000000000000000000000101010 Z
1[
1]
b00000000000000000000000000000000 ^
b00000000000000000000000000101010 c
b000000000000000000000000000000000000000000000000 d
b000000000000000000000000000000000000000000000000 f
#145002
0#
01
0L
0R
0[
#150002
1#
b00101010 .
b00000000000000000000000000101010 0
11
b00101010 <
b00000000000000000000000000101010 >
0?
1B
b00000000000000000000000000000000 C
b00101010 D
b000000000000000000000000000000000000000000000000 F
b000000000000000000000000000000000000000010000000 H
b00000000000000000000000000000000 J
b00000000000000000000000000000000 K
1L
0P
1R
1T
b00000000000000000000000000000000 U
b00000000000000000000000000101010 X
b00000000000000000000000000000000 Y
b00000000000000000000000000000000 Z
1[
0]
1b
b00000000000000000000000000000000 c
#155002
0#
01
0L
0R
0[
#160002
1#
1-
b00000000 .
1/
b00000000000000000000000000000000 0
11
1;
b00000000 <
1=
b00000000000000000000000000000000 >
0B
b00000000 D
1E
1L
1R
0T
1W
b00000000000000000000000000000000 X
1[
0b
#165002
0#
01
0L
0R
0[
#170002
1#
0-
0/
11
0;
0=
0E
1L
1R
0W
1[
#175002
0#
01
0L
0R
0[
#180002
1#
11
1L
1R
1[
#185002
0#
01
0L
0R
0[
#190002
1#
11
1L
1R
1[
#190003
1$
12
1M
1S
1\
#195003
0#
01
0L
0R
0[
#200003
1#
11
1L
1R
1[
#205003
0#
01
0L
0R
0[
#210003
1#
0$
11
02
1L
0M
1R
0S
1[
0\
#215003
0#
01
0L
0R
0[
#220003
1#
1%
b00000000000000000000000011001000 &
11
13
b00000000000000000000000011001000 4
1L
1N
b00000000000000000000000011001000 O
1R
1[
#225003
0#
01
0L
0R
0[
#230003
1#
0%
11
03
1?
b00000000000000000000000011001000 @
1L
0N
1P
b00000000000000000000000011001000 Q
1R
1[
1]
b00000000000000000000000011001000 ^
b000000000000000000000000000000001100100000000000 d
b000000000000000000000000000000000000000011001000 f
#235003
0#
01
0L
0R
0[
#240003
1#
11
0?
1B
b00000000000000000000000011001000 C
b000000000000000000000000000000001100100000000000 F
b000000000000000000000000000000001100100010000000 H
b00000000000000000000000011001000 J
b00000000000000000000000011001000 K
1L
0P
1R
1T
b00000000000000000000000011001000 U
b00000000000000000000000011001000 Y
b00000000000000000000000011001000 Z
1[
0]
1b
b00000000000000000000000011001000 c
#245003
0#
01
0L
0R
0[
#250003
1#
1-
b01111111 .
1/
b00000000000000000000000011001000 0
11
1;
b01111111 <
1=
b00000000000000000000000011001000 >
0B
b01111111 D
1E
1L
1R
0T
1W
b00000000000000000000000011001000 X
1[
0b
#255003
0#
01
0L
0R
0[
#260003
1#
0-
0/
11
0;
0=
0E
1L
1R
0W
1[
