rtl/activation_func.sv
`timescale 1ns / 1ps

// Simple activation block with selectable function.
// DEFAULT_ACT: 00=passthrough, 01=ReLU, 10=ReLU6 (clamps to 6)
module activation_func #(
    parameter logic [1:0] DEFAULT_ACT = 2'b01
) (
    input  logic        clk,
    input  logic        reset,
    input  logic        valid_in,
    input  logic signed [31:0] data_in,
    output logic        valid_out,
    output logic signed [31:0] data_out
);

    always_ff @(posedge clk or posedge reset) begin
        if (reset) begin
            valid_out <= 1'b0;
            data_out  <= 32'sd0;
        end else begin
            valid_out <= valid_in;
            unique case (DEFAULT_ACT)
                2'b00: data_out <= data_in;                          // passthrough
                2'b01: data_out <= data_in[31] ? 32'sd0 : data_in;   // ReLU
                2'b10: begin                                         // ReLU6 (clamp to 6)
                    if (data_in[31])
                        data_out <= 32'sd0;
                    else if (data_in > 32'sd6)
                        data_out <= 32'sd6;
                    else
                        data_out <= data_in;
                end
                default: data_out <= data_in;
            endcase
        end
    end

endmodule

sim/waves/activation_func.vcd
$version Generated by VerilatedVcd $end
$timescale 1ps $end
 $scope module $rootio $end
  $var wire 1 # clk $end
  $var wire 1 $ reset $end
  $var wire 1 % valid_in $end
  $var wire 32 & data_in [31:0] $end
  $var wire 1 ' valid_out $end
  $var wire 32 ( data_out [31:0] $end
 $upscope $end
 $scope module activation_func $end
  $var wire 2 / DEFAULT_ACT [1:0] $end
  $var wire 1 ) clk $end
  $var wire 1 * reset $end
  $var wire 1 + valid_in $end
  $var wire 32 , data_in [31:0] $end
  $var wire 1 - valid_out $end
  $var wire 32 . data_out [31:0] $end
 $upscope $end
$enddefinitions $end


#0
1#
1$
0%
b00000000000000000000000000000000 &
0'
b00000000000000000000000000000000 (
1)
1*
0+
b00000000000000000000000000000000 ,
0-
b00000000000000000000000000000000 .
b01 /
#5000
0#
0)
#10000
1#
1)
#15001
0#
0)
#20001
1#
1)
#25001
0#
0)
#30001
1#
0$
1)
0*
#35001
0#
0)
#40001
1#
1%
b00000000000000000000000000101010 &
1)
1+
b00000000000000000000000000101010 ,
#45001
0#
0)
#50001
1#
1'
b00000000000000000000000000101010 (
1)
1-
b00000000000000000000000000101010 .
#55001
0#
0)
#60001
1#
1)
#60002
1$
0'
b00000000000000000000000000000000 (
1*
0-
b00000000000000000000000000000000 .
#65002
0#
0)
#70002
1#
1)
#75002
0#
0)
#80002
1#
0$
1)
0*
#85002
0#
0)
#90002
1#
b11111111111111111111111111110110 &
1'
b00000000000000000000000000101010 (
1)
b11111111111111111111111111110110 ,
1-
b00000000000000000000000000101010 .
#95002
0#
0)
#100002
1#
b00000000000000000000000000000000 (
1)
b00000000000000000000000000000000 .
#105002
0#
0)
#110002
1#
1)
#110003
1$
0'
1*
0-
#115003
0#
0)
#120003
1#
1)
#125003
0#
0)
#130003
1#
0$
1)
0*
#135003
0#
0)
#140003
1#
b00000000000000000000000000000000 &
1'
1)
b00000000000000000000000000000000 ,
1-
