rtl/dual_weight_fifo.sv
`timescale 1ns / 1ps

module dual_weight_fifo (
    input  logic       clk,
    input  logic       reset,
    // Push interface
    // Simulates a narrow bus filling multiple columns
    input  logic       push_col0,
    input  logic       push_col1,
    input  logic [7:0] data_in, // Shared Data Bus
    // Pop interface
    // The MMU loads weights with column staggering
    input  logic       pop,
    output logic [7:0] col0_out,      // Direct output (combinational, no skew)
    output logic [7:0] col1_out,      // Skewed output (1-cycle delay for diagonal wavefront)
    // Raw outputs (for debugging/monitoring)
    output logic [7:0] col1_raw       // Pre-skew col1 value (for debugging)
);

    // Two 4-deep queues
    logic [7:0] queue0 [4];
    logic [7:0] queue1 [4];

    // Pointers for read/write
    logic [1:0] wr_ptr0, rd_ptr0;
    logic [1:0] wr_ptr1, rd_ptr1;

    // Column 0: Combinational read (no skew, no latency)
    assign col0_out = queue0[rd_ptr0];

    // Column 1 raw value (pre-skew, for debugging)
    assign col1_raw = queue1[rd_ptr1];

    always_ff @(posedge clk or posedge reset) begin
        if (reset) begin
            wr_ptr0 <= 2'd0;
            rd_ptr0 <= 2'd0;
            wr_ptr1 <= 2'd0;
            rd_ptr1 <= 2'd0;
            col1_out <= 8'd0;
            // Initialize queues
            queue0[0] <= 8'd0;
            queue0[1] <= 8'd0;
            queue0[2] <= 8'd0;
            queue0[3] <= 8'd0;
            queue1[0] <= 8'd0;
            queue1[1] <= 8'd0;
            queue1[2] <= 8'd0;
            queue1[3] <= 8'd0;
        end else begin
            // Column 0: Push and Pop (no skew)
            if (push_col0) begin
                queue0[wr_ptr0] <= data_in;
                wr_ptr0 <= wr_ptr0 + 1'd1;
            end
            if (pop) begin
                rd_ptr0 <= rd_ptr0 + 1'd1;
            end

            // Column 1: Push and Pop with 1-cycle skew
            // The skew register delays col1 output by 1 cycle for diagonal wavefront
            if (push_col1) begin
                queue1[wr_ptr1] <= data_in;
                wr_ptr1 <= wr_ptr1 + 1'd1;
            end
            if (pop) begin
                // Output current queue value (this is the 1-cycle delayed value)
                col1_out <= queue1[rd_ptr1];
                rd_ptr1 <= rd_ptr1 + 1'd1;
            end
        end
    end

endmodule

sim/waves/dual_weight_fifo.vcd
$version Generated by VerilatedVcd $end
$timescale 1ps $end
 $scope module $rootio $end
  $var wire 1 # clk $end
  $var wire 1 $ reset $end
  $var wire 1 % push_col0 $end
  $var wire 1 & push_col1 $end
  $var wire 8 ' data_in [7:0] $end
  $var wire 1 ( pop $end
  $var wire 8 ) col0_out [7:0] $end
  $var wire 8 * col1_out [7:0] $end
  $var wire 8 + col1_raw [7:0] $end
 $upscope $end
 $scope module dual_weight_fifo $end
  $var wire 1 , clk $end
  $var wire 1 - reset $end
  $var wire 1 . push_col0 $end
  $var wire 1 / push_col1 $end
  $var wire 8 0 data_in [7:0] $end
  $var wire 1 1 pop $end
  $var wire 8 2 col0_out [7:0] $end
  $var wire 8 3 col1_out [7:0] $end
  $var wire 8 4 col1_raw [7:0] $end
  $var wire 8 5 queue0[0] [7:0] $end
  $var wire 8 6 queue0[1] [7:0] $end
  $var wire 8 7 queue0[2] [7:0] $end
  $var wire 8 8 queue0[3] [7:0] $end
  $var wire 8 9 queue1[0] [7:0] $end
  $var wire 8 : queue1[1] [7:0] $end
  $var wire 8 ; queue1[2] [7:0] $end
  $var wire 8 < queue1[3] [7:0] $end
  $var wire 2 = wr_ptr0 [1:0] $end
  $var wire 2 > rd_ptr0 [1:0] $end
  $var wire 2 ? wr_ptr1 [1:0] $end
  $var wire 2 @ rd_ptr1 [1:0] $end
 $upscope $end
$enddefinitions $end


#0
1#
1$
0%
0&
b00000000 '
0(
b00000000 )
b00000000 *
b00000000 +
1,
1-
0.
0/
b00000000 0
01
b00000000 2
b00000000 3
b00000000 4
b00000000 5
b00000000 6
b00000000 7
b00000000 8
b00000000 9
b00000000 :
b00000000 ;
b00000000 <
b00 =
b00 >
b00 ?
b00 @
#5000
0#
0,
#10000
1#
1,
#15001
0#
0,
#20001
1#
1,
#25001
0#
0,
#30001
1#
0$
1,
0-
#35001
0#
0,
#40001
1#
1%
b00001011 '
1,
1.
b00001011 0
#45001
0#
0,
#50001
1#
b00001100 '
b00001011 )
1,
b00001100 0
b00001011 2
b00001011 5
b01 =
#55001
0#
0,
#60001
1#
0%
1&
b00010101 '
1,
0.
1/
b00010101 0
b00001100 6
b10 =
#65001
0#
0,
#70001
1#
b00010110 '
b00010101 +
1,
b00010110 0
b00010101 4
b00010101 9
b01 ?
#75001
0#
0,
#80001
1#
0&
1,
0/
b00010110 :
b10 ?
#85001
0#
0,
#90001
1#
1(
1,
11
#95001
0#
0,
#100001
1#
b00001100 )
b00010101 *
b00010110 +
1,
b00001100 2
b00010101 3
b00010110 4
b01 >
b01 @
#105001
0#
0,
#110001
1#
0(
b00000000 )
b00010110 *
b00000000 +
1,
01
b00000000 2
b00010110 3
b00000000 4
b10 >
b10 @
#110002
1$
b00000000 *
1-
b00000000 3
b00000000 5
b00000000 6
b00000000 9
b00000000 :
b00 =
b00 >
b00 ?
b00 @
#115002
0#
0,
#120002
1#
1,
#125002
0#
0,
#130002
1#
0$
1,
0-
#135002
0#
0,
#140002
1#
1%
b01100100 '
1,
1.
b01100100 0
#145002
0#
0,
#150002
1#
b11001000 '
b01100100 )
1,
b11001000 0
b01100100 2
b01100100 5
b01 =
#155002
0#
0,
#160002
1#
0%
1&
b01100100 '
1,
0.
1/
b01100100 0
b11001000 6
b10 =
#165002
0#
0,
#170002
1#
b11001000 '
b01100100 +
1,
b11001000 0
b01100100 4
b01100100 9
b01 ?
#175002
0#
0,
#180002
1#
0&
1,
0/
b11001000 :
b10 ?
#185002
0#
0,
#190002
1#
1(
1,
11
#195002
0#
0,
#200002
1#
b11001000 )
b01100100 *
b11001000 +
1,
b11001000 2
b01100100 3
b11001000 4
b01 >
b01 @
#205002
0#
0,
#210002
1#
0(
b00000000 )
b11001000 *
b00000000 +
1,
01
b00000000 2
b11001000 3
b00000000 4
b10 >
b10 @
