rtl/pe.sv
`timescale 1ns / 1ps

module pe (
    input  logic        clk,
    input  logic        reset,
    input  logic        en_weight_pass,    // Pass in_psum through out_psum (always during load phase)
    input  logic        en_weight_capture, // Capture weight from in_psum (per-PE timing for diagonal)
    input  logic [7:0]  in_act,
    input  logic [15:0] in_psum,
    output logic [7:0]  out_act,
    output logic [15:0] out_psum
);

    logic [7:0] weight;

    always_ff @(posedge clk or posedge reset) begin
        if (reset) begin
            out_act <= 8'd0;
            out_psum <= 16'd0;
            weight <= 8'd0;
        end
        else begin
            if (en_weight_pass) begin
                // Weight loading mode: pass psum through, reset activation
                out_psum <= in_psum;
                out_act <= 8'd0;
                // Capture weight only when this PE's capture signal is active
                if (en_weight_capture) begin
                    weight <= in_psum[7:0];
                end
            end
            else begin
                // Compute mode: MAC operation
                out_act <= in_act;
                out_psum <= (in_act * weight) + in_psum;
            end
        end
    end

endmodule

rtl/mmu.sv
`timescale 1ns / 1ps

module mmu ( // for a 2x2 systolic array
    input  logic        clk,
    input  logic        reset,
    input  logic        en_weight_pass,      // Pass psum through all PEs (always during load phase)
    input  logic        en_capture_col0,     // Capture enable for column 0 PEs (PE00, PE10)
    input  logic        en_capture_col1,     // Capture enable for column 1 PEs (PE01, PE11)

    // UB activations input
    input  logic [7:0]  row0_in,
    input  logic [7:0]  row1_in,

    // Weight FIFO input
    input  logic [7:0]  col0_in,
    input  logic [7:0]  col1_in,

    // Accumulator output
    output logic [15:0] acc0_out,
    output logic [15:0] acc1_out
);

    // PE Layout:
    // pe00 -> pe01    Activations flow horizontally (right)
    //   |       |
    //   v       v     Partial sums flow vertically (down)
    // pe10 -> pe11
    //   |       |
    //   v       v
    // acc0   acc1

    // Systolic array PE connections
    logic [7:0] pe00_01_act, pe10_11_act;
    logic [15:0] pe00_10_psum, pe01_11_psum;

    pe pe00 (
        .clk(clk),
        .reset(reset),
        .en_weight_pass(en_weight_pass),
        .en_weight_capture(en_capture_col0),  // Column 0 capture timing
        .in_act(row0_in),
        .in_psum({8'b0, col0_in}),
        .out_act(pe00_01_act),
        .out_psum(pe00_10_psum)
    );

    pe pe01 (
        .clk(clk),
        .reset(reset),
        .en_weight_pass(en_weight_pass),
        .en_weight_capture(en_capture_col1),  // Column 1 capture timing (staggered)
        .in_act(pe00_01_act),
        .in_psum({8'b0, col1_in}),
        .out_act(), // Activation unconnected at edge of 2x2 array
        .out_psum(pe01_11_psum)
    );

    pe pe10 (
        .clk(clk),
        .reset(reset),
        .en_weight_pass(en_weight_pass),
        .en_weight_capture(en_capture_col0),  // Column 0 capture timing
        .in_act(row1_in),
        .in_psum(pe00_10_psum),
        .out_act(pe10_11_act),
        .out_psum(acc0_out)       // Output column 0 to accumulator
    );

    pe pe11 (
        .clk(clk),
        .reset(reset),
        .en_weight_pass(en_weight_pass),
        .en_weight_capture(en_capture_col1),  // Column 1 capture timing (staggered)
        .in_act(pe10_11_act),
        .in_psum(pe01_11_psum),
        .out_act(), // Activation unconnected at edge of 2x2 array
        .out_psum(acc1_out)       // Output column 1 to accumulator
    );

endmodule

sim/waves/mmu.vcd
$version Generated by VerilatedVcd $end
$timescale 1ps $end
 $scope module $rootio $end
  $var wire 1 # clk $end
  $var wire 1 $ reset $end
  $var wire 1 % en_weight_pass $end
  $var wire 1 & en_capture_col0 $end
  $var wire 1 ' en_capture_col1 $end
  $var wire 8 ( row0_in [7:0] $end
  $var wire 8 ) row1_in [7:0] $end
  $var wire 8 * col0_in [7:0] $end
  $var wire 8 + col1_in [7:0] $end
  $var wire 16 , acc0_out [15:0] $end
  $var wire 16 - acc1_out [15:0] $end
 $upscope $end
 $scope module mmu $end
  $var wire 1 . clk $end
  $var wire 1 / reset $end
  $var wire 1 0 en_weight_pass $end
  $var wire 1 1 en_capture_col0 $end
  $var wire 1 2 en_capture_col1 $end
  $var wire 8 3 row0_in [7:0] $end
  $var wire 8 4 row1_in [7:0] $end
  $var wire 8 5 col0_in [7:0] $end
  $var wire 8 6 col1_in [7:0] $end
  $var wire 16 7 acc0_out [15:0] $end
  $var wire 16 8 acc1_out [15:0] $end
  $var wire 8 9 pe00_01_act [7:0] $end
  $var wire 8 : pe10_11_act [7:0] $end
  $var wire 16 ; pe00_10_psum [15:0] $end
  $var wire 16 < pe01_11_psum [15:0] $end
  $scope module pe00 $end
   $var wire 1 = clk $end
   $var wire 1 > reset $end
   $var wire 1 ? en_weight_pass $end
   $var wire 1 @ en_weight_capture $end
   $var wire 8 A in_act [7:0] $end
   $var wire 16 B in_psum [15:0] $end
   $var wire 8 C out_act [7:0] $end
   $var wire 16 D out_psum [15:0] $end
   $var wire 8 E weight [7:0] $end
  $upscope $end
  $scope module pe01 $end
   $var wire 1 F clk $end
   $var wire 1 G reset $end
   $var wire 1 H en_weight_pass $end
   $var wire 1 I en_weight_capture $end
   $var wire 8 J in_act [7:0] $end
   $var wire 16 K in_psum [15:0] $end
   $var wire 8 L out_act [7:0] $end
   $var wire 16 M out_psum [15:0] $end
   $var wire 8 N weight [7:0] $end
  $upscope $end
  $scope module pe10 $end
   $var wire 1 O clk $end
   $var wire 1 P reset $end
   $var wire 1 Q en_weight_pass $end
   $var wire 1 R en_weight_capture $end
   $var wire 8 S in_act [7:0] $end
   $var wire 16 T in_psum [15:0] $end
   $var wire 8 U out_act [7:0] $end
   $var wire 16 V out_psum [15:0] $end
   $var wire 8 W weight [7:0] $end
  $upscope $end
  $scope module pe11 $end
   $var wire 1 X clk $end
   $var wire 1 Y reset $end
   $var wire 1 Z en_weight_pass $end
   $var wire 1 [ en_weight_capture $end
   $var wire 8 \ in_act [7:0] $end
   $var wire 16 ] in_psum [15:0] $end
   $var wire 8 ^ out_act [7:0] $end
   $var wire 16 _ out_psum [15:0] $end
   $var wire 8 ` weight [7:0] $end
  $upscope $end
 $upscope $end
$enddefinitions $end


#0
1#
1$
0%
0&
0'
b00000000 (
b00000000 )
b00000000 *
b00000000 +
b0000000000000000 ,
b0000000000000000 -
1.
1/
00
01
02
b00000000 3
b00000000 4
b00000000 5
b00000000 6
b0000000000000000 7
b0000000000000000 8
b00000000 9
b00000000 :
b0000000000000000 ;
b0000000000000000 <
1=
1>
0?
0@
b00000000 A
b0000000000000000 B
b00000000 C
b0000000000000000 D
b00000000 E
1F
1G
0H
0I
b00000000 J
b0000000000000000 K
b00000000 L
b0000000000000000 M
b00000000 N
1O
1P
0Q
0R
b00000000 S
b0000000000000000 T
b00000000 U
b0000000000000000 V
b00000000 W
1X
1Y
0Z
0[
b00000000 \
b0000000000000000 ]
b00000000 ^
b0000000000000000 _
b00000000 `
#5000
0#
0.
0=
0F
0O
0X
#10000
1#
1.
1=
1F
1O
1X
#15001
0#
0.
0=
0F
0O
0X
#20001
1#
1.
1=
1F
1O
1X
#25001
0#
0.
0=
0F
0O
0X
#30001
1#
0$
1.
0/
1=
0>
1F
0G
1O
0P
1X
0Y
#35001
0#
0.
0=
0F
0O
0X
#40001
1#
1%
1&
b00000011 *
b00000100 +
1.
10
11
b00000011 5
b00000100 6
1=
1?
1@
b0000000000000011 B
1F
1H
b0000000000000100 K
1O
1Q
1R
1X
1Z
#45001
0#
0.
0=
0F
0O
0X
#50001
1#
1'
b00000001 *
b00000010 +
1.
12
b00000001 5
b00000010 6
b0000000000000011 ;
b0000000000000100 <
1=
b0000000000000001 B
b0000000000000011 D
b00000011 E
1F
1I
b0000000000000010 K
b0000000000000100 M
1O
b0000000000000011 T
1X
1[
b0000000000000100 ]
#55001
0#
0.
0=
0F
0O
0X
#60001
1#
0&
b0000000000000011 ,
b0000000000000100 -
1.
01
b0000000000000011 7
b0000000000000100 8
b0000000000000001 ;
b0000000000000010 <
1=
0@
b0000000000000001 D
b00000001 E
1F
b0000000000000010 M
b00000010 N
1O
0R
b0000000000000001 T
b0000000000000011 V
b00000011 W
1X
b0000000000000010 ]
b0000000000000100 _
b00000100 `
#65001
0#
0.
0=
0F
0O
0X
#70001
1#
0%
0'
b0000000000000001 ,
b0000000000000010 -
1.
00
02
b0000000000000001 7
b0000000000000010 8
1=
0?
1F
0H
0I
1O
0Q
b0000000000000001 V
1X
0Z
0[
b0000000000000010 _
b00000010 `
#70002
1$
b00000000 *
b00000000 +
b0000000000000000 ,
b0000000000000000 -
1/
b00000000 5
b00000000 6
b0000000000000000 7
b0000000000000000 8
b0000000000000000 ;
b0000000000000000 <
1>
b0000000000000000 B
b0000000000000000 D
b00000000 E
1G
b0000000000000000 K
b0000000000000000 M
b00000000 N
1P
b0000000000000000 T
b0000000000000000 V
b00000000 W
1Y
b0000000000000000 ]
b0000000000000000 _
b00000000 `
#75002
0#
0.
0=
0F
0O
0X
#80002
1#
1.
1=
1F
1O
1X
#85002
0#
0.
0=
0F
0O
0X
#90002
1#
0$
1.
0/
1=
0>
1F
0G
1O
0P
1X
0Y
#95002
0#
0.
0=
0F
0O
0X
#100002
1#
1%
1&
b00000011 *
b00000100 +
1.
10
11
b00000011 5
b00000100 6
1=
1?
1@
b0000000000000011 B
1F
1H
b0000000000000100 K
1O
1Q
1R
1X
1Z
#105002
0#
0.
0=
0F
0O
0X
#110002
1#
1'
b00000001 *
b00000010 +
1.
12
b00000001 5
b00000010 6
b0000000000000011 ;
b0000000000000100 <
1=
b0000000000000001 B
b0000000000000011 D
b00000011 E
1F
1I
b0000000000000010 K
b0000000000000100 M
1O
b0000000000000011 T
1X
1[
b0000000000000100 ]
#115002
0#
0.
0=
0F
0O
0X
#120002
1#
0&
b0000000000000011 ,
b0000000000000100 -
1.
01
b0000000000000011 7
b0000000000000100 8
b0000000000000001 ;
b0000000000000010 <
1=
0@
b0000000000000001 D
b00000001 E
1F
b0000000000000010 M
b00000010 N
1O
0R
b0000000000000001 T
b0000000000000011 V
b00000011 W
1X
b0000000000000010 ]
b0000000000000100 _
b00000100 `
#125002
0#
0.
0=
0F
0O
0X
#130002
1#
0%
0'
b00001010 (
b00000000 *
b00000000 +
b0000000000000001 ,
b0000000000000010 -
1.
00
02
b00001010 3
b00000000 5
b00000000 6
b0000000000000001 7
b0000000000000010 8
1=
0?
b00001010 A
b0000000000000000 B
1F
0H
0I
b0000000000000000 K
1O
0Q
b0000000000000001 V
1X
0Z
0[
b0000000000000010 _
b00000010 `
#135002
0#
0.
0=
0F
0O
0X
#140002
1#
b00010100 (
b00011110 )
1.
b00010100 3
b00011110 4
b00001010 9
b0000000000001010 ;
b0000000000000000 <
1=
b00010100 A
b00001010 C
b0000000000001010 D
1F
b00001010 J
b0000000000000000 M
1O
b00011110 S
b0000000000001010 T
1X
b0000000000000000 ]
#145002
0#
0.
0=
0F
0O
0X
#150002
1#
b00000000 (
b00101000 )
b0000000001100100 ,
b0000000000000000 -
1.
b00000000 3
b00101000 4
b0000000001100100 7
b0000000000000000 8
b00010100 9
b00011110 :
b0000000000010100 ;
b0000000000010100 <
1=
b00000000 A
b00010100 C
b0000000000010100 D
1F
b00010100 J
b00001010 L
b0000000000010100 M
1O
b00101000 S
b0000000000010100 T
b00011110 U
b0000000001100100 V
1X
b00011110 \
b0000000000010100 ]
b0000000000000000 _
#155002
0#
0.
0=
0F
0O
0X
#160002
1#
b00000000 )
b0000000010001100 ,
b0000000001010000 -
1.
b00000000 4
b0000000010001100 7
b0000000001010000 8
b00000000 9
b00101000 :
b0000000000000000 ;
b0000000000101000 <
1=
b00000000 C
b0000000000000000 D
1F
b00000000 J
b00010100 L
b0000000000101000 M
1O
b00000000 S
b0000000000000000 T
b00101000 U
b0000000010001100 V
1X
b00101000 \
b0000000000101000 ]
b00011110 ^
b0000000001010000 _
#165002
0#
0.
0=
0F
0O
0X
#170002
1#
b0000000000000000 ,
b0000000001111000 -
1.
b0000000000000000 7
b0000000001111000 8
b00000000 :
b0000000000000000 <
1=
1F
b00000000 L
b0000000000000000 M
1O
b00000000 U
b0000000000000000 V
1X
b00000000 \
b0000000000000000 ]
b00101000 ^
b0000000001111000 _
#175002
0#
0.
0=
0F
0O
0X
#180002
1#
b0000000000000000 -
1.
b0000000000000000 8
1=
1F
1O
1X
b00000000 ^
b0000000000000000 _
#185002
0#
0.
0=
0F
0O
0X
#190002
1#
1.
1=
1F
1O
1X
#190003
1$
1/
1>
b00000000 E
1G
b00000000 N
1P
b00000000 W
1Y
b00000000 `
#195003
0#
0.
0=
0F
0O
0X
#200003
1#
1.
1=
1F
1O
1X
#205003
0#
0.
0=
0F
0O
0X
#210003
1#
0$
1.
0/
1=
0>
1F
0G
1O
0P
1X
0Y
#215003
0#
0.
0=
0F
0O
0X
#220003
1#
1.
1=
1F
1O
1X
#225003
0#
0.
0=
0F
0O
0X
#230003
1#
1%
1&
b00000001 +
1.
10
11
b00000001 6
1=
1?
1@
1F
1H
b0000000000000001 K
1O
1Q
1R
1X
1Z
#235003
0#
0.
0=
0F
0O
0X
#240003
1#
1'
b00000001 *
b00000000 +
1.
12
b00000001 5
b00000000 6
b0000000000000001 <
1=
b0000000000000001 B
1F
1I
b0000000000000000 K
b0000000000000001 M
1O
1X
1[
b0000000000000001 ]
#245003
0#
0.
0=
0F
0O
0X
#250003
1#
0&
b0000000000000001 -
1.
01
b0000000000000001 8
b0000000000000001 ;
b0000000000000000 <
1=
0@
b0000000000000001 D
b00000001 E
1F
b0000000000000000 M
1O
0R
b0000000000000001 T
1X
b0000000000000000 ]
b0000000000000001 _
b00000001 `
#255003
0#
0.
0=
0F
0O
0X
#260003
1#
0%
0'
b00000101 (
b00000000 *
b0000000000000001 ,
b0000000000000000 -
1.
00
02
b00000101 3
b00000000 5
b0000000000000001 7
b0000000000000000 8
1=
0?
b00000101 A
b0000000000000000 B
1F
0H
0I
1O
0Q
b0000000000000001 V
1X
0Z
0[
b0000000000000000 _
b00000000 `
#265003
0#
0.
0=
0F
0O
0X
#270003
1#
b00000110 (
b00000111 )
1.
b00000110 3
b00000111 4
b00000101 9
b0000000000000101 ;
1=
b00000110 A
b00000101 C
b0000000000000101 D
1F
b00000101 J
1O
b00000111 S
b0000000000000101 T
1X
#275003
0#
0.
0=
0F
0O
0X
#280003
1#
b00000000 (
b00001000 )
b0000000000000101 ,
1.
b00000000 3
b00001000 4
b0000000000000101 7
b00000110 9
b00000111 :
b0000000000000110 ;
1=
b00000000 A
b00000110 C
b0000000000000110 D
1F
b00000110 J
b00000101 L
1O
b00001000 S
b0000000000000110 T
b00000111 U
b0000000000000101 V
1X
b00000111 \
#285003
0#
0.
0=
0F
0O
0X
#290003
1#
b00000000 )
b0000000000000110 ,
1.
b00000000 4
b0000000000000110 7
b00000000 9
b00001000 :
b0000000000000000 ;
1=
b00000000 C
b0000000000000000 D
1F
b00000000 J
b00000110 L
1O
b00000000 S
b0000000000000000 T
b00001000 U
b0000000000000110 V
1X
b00001000 \
b00000111 ^
#295003
0#
0.
0=
0F
0O
0X
#300003
1#
b0000000000000000 ,
1.
b0000000000000000 7
b00000000 :
1=
1F
b00000000 L
1O
b00000000 U
b0000000000000000 V
1X
b00000000 \
b00001000 ^
#305003
0#
0.
0=
0F
0O
0X
#310003
1#
1.
1=
1F
1O
1X
b00000000 ^
