rtl/normalizer.sv
`timescale 1ns / 1ps

// Fixed-point normalization: (data_in * gain) >> shift + bias
// gain is signed Qm.n; shift controls right shift to rescale.
module normalizer (
    input  logic        clk,
    input  logic        reset,
    input  logic        valid_in,
    input  logic signed [31:0] data_in,
    input  logic signed [15:0] gain,
    input  logic signed [31:0] bias,
    input  logic [4:0]  shift,
    output logic        valid_out,
    output logic signed [31:0] data_out
);

    // Wider product to hold intermediate result
    logic signed [47:0] mult;
    logic signed [47:0] shifted;

    assign mult = data_in * gain;
    assign shifted = mult >>> shift;

    always_ff @(posedge clk or posedge reset) begin
        if (reset) begin
            valid_out <= 1'b0;
            data_out  <= 32'sd0;
        end else begin
            valid_out <= valid_in;
            data_out  <= shifted[31:0] + bias;
        end
    end

endmodule

sim/waves/normalizer.vcd
$version Generated by VerilatedVcd $end
$timescale 1ps $end
 $scope module $rootio $end
  $var wire 1 # clk $end
  $var wire 1 $ reset $end
  $var wire 1 % valid_in $end
  $var wire 32 & data_in [31:0] $end
  $var wire 16 ' gain [15:0] $end
  $var wire 32 ( bias [31:0] $end
  $var wire 5 ) shift [4:0] $end
  $var wire 1 * valid_out $end
  $var wire 32 + data_out [31:0] $end
 $upscope $end
 $scope module normalizer $end
  $var wire 1 , clk $end
  $var wire 1 - reset $end
  $var wire 1 . valid_in $end
  $var wire 32 / data_in [31:0] $end
  $var wire 16 0 gain [15:0] $end
  $var wire 32 1 bias [31:0] $end
  $var wire 5 2 shift [4:0] $end
  $var wire 1 3 valid_out $end
  $var wire 32 4 data_out [31:0] $end
  $var wire 48 5 mult [47:0] $end
  $var wire 48 7 shifted [47:0] $end
 $upscope $end
$enddefinitions $end


#0
1#
1$
0%
b00000000000000000000000000000000 &
b0000000000000000 '
b00000000000000000000000000000000 (
b00000 )
0*
b00000000000000000000000000000000 +
1,
1-
0.
b00000000000000000000000000000000 /
b0000000000000000 0
b00000000000000000000000000000000 1
b00000 2
03
b00000000000000000000000000000000 4
b000000000000000000000000000000000000000000000000 5
b000000000000000000000000000000000000000000000000 7
#5000
0#
0,
#10000
1#
0$
1,
0-
#15000
0#
0,
#20000
1#
1%
b00000000000000000000000001100100 &
b0000000100000000 '
b01000 )
1,
1.
b00000000000000000000000001100100 /
b0000000100000000 0
b01000 2
b000000000000000000000000000000000110010000000000 5
b000000000000000000000000000000000000000001100100 7
#25000
0#
0,
#30000
1#
1*
b00000000000000000000000001100100 +
1,
13
b00000000000000000000000001100100 4
#35000
0#
0,
#40000
1#
1,
#40001
1$
0*
b00000000000000000000000000000000 +
1-
03
b00000000000000000000000000000000 4
#45001
0#
0,
#50001
1#
1,
#55001
0#
0,
#60001
1#
0$
1,
0-
#65001
0#
0,
#70001
1#
b00000000000000000000000000110010 (
1*
b00000000000000000000000001100100 +
1,
b00000000000000000000000000110010 1
13
b00000000000000000000000001100100 4
#75001
0#
0,
#80001
1#
b00000000000000000000000010010110 +
1,
b00000000000000000000000010010110 4
#85001
0#
0,
#90001
1#
1,
#90002
1$
0*
b00000000000000000000000000000000 +
1-
03
b00000000000000000000000000000000 4
#95002
0#
0,
#100002
1#
1,
#105002
0#
0,
#110002
1#
0$
1,
0-
#115002
0#
0,
#120002
1#
b00000000000000000000000000110010 &
b0000001000000000 '
b00000000000000000000000000000000 (
1*
b00000000000000000000000010010110 +
1,
b00000000000000000000000000110010 /
b0000001000000000 0
b00000000000000000000000000000000 1
13
b00000000000000000000000010010110 4
#125002
0#
0,
#130002
1#
b00000000000000000000000001100100 +
1,
b00000000000000000000000001100100 4
