rtl/pe.sv
`timescale 1ns / 1ps

module pe (
    input  logic        clk,
    input  logic        reset,
    input  logic        en_weight_pass,    // Pass in_psum through out_psum (always during load phase)
    input  logic        en_weight_capture, // Capture weight from in_psum (per-PE timing for diagonal)
    input  logic [7:0]  in_act,
    input  logic [15:0] in_psum,
    output logic [7:0]  out_act,
    output logic [15:0] out_psum
);

    logic [7:0] weight;

    always_ff @(posedge clk or posedge reset) begin
        if (reset) begin
            out_act <= 8'd0;
            out_psum <= 16'd0;
            weight <= 8'd0;
        end
        else begin
            if (en_weight_pass) begin
                // Weight loading mode: pass psum through, reset activation
                out_psum <= in_psum;
                out_act <= 8'd0;
                // Capture weight only when this PE's capture signal is active
                if (en_weight_capture) begin
                    weight <= in_psum[7:0];
                end
            end
            else begin
                // Compute mode: MAC operation
                out_act <= in_act;
                out_psum <= (in_act * weight) + in_psum;
            end
        end
    end

endmodule

sim/waves/pe.vcd
$version Generated by VerilatedVcd $end
$timescale 1ps $end
 $scope module $rootio $end
  $var wire 1 # clk $end
  $var wire 1 $ reset $end
  $var wire 1 % en_weight_pass $end
  $var wire 1 & en_weight_capture $end
  $var wire 8 ' in_act [7:0] $end
  $var wire 16 ( in_psum [15:0] $end
  $var wire 8 ) out_act [7:0] $end
  $var wire 16 * out_psum [15:0] $end
 $upscope $end
 $scope module pe $end
  $var wire 1 + clk $end
  $var wire 1 , reset $end
  $var wire 1 - en_weight_pass $end
  $var wire 1 . en_weight_capture $end
  $var wire 8 / in_act [7:0] $end
  $var wire 16 0 in_psum [15:0] $end
  $var wire 8 1 out_act [7:0] $end
  $var wire 16 2 out_psum [15:0] $end
  $var wire 8 3 weight [7:0] $end
 $upscope $end
$enddefinitions $end


#0
1#
1$
0%
0&
b00000000 '
b0000000000000000 (
b00000000 )
b0000000000000000 *
1+
1,
0-
0.
b00000000 /
b0000000000000000 0
b00000000 1
b0000000000000000 2
b00000000 3
#5000
0#
0+
#10000
1#
1+
#15001
0#
0+
#20001
1#
1+
#25001
0#
0+
#30001
1#
0$
1+
0,
#35001
0#
0+
#40001
1#
1%
b0000000000101010 (
1+
1-
b0000000000101010 0
#45001
0#
0+
#50001
1#
b0000000000101010 *
1+
b0000000000101010 2
#55001
0#
0+
#60001
1#
1+
#60002
1$
b0000000000000000 *
1,
b0000000000000000 2
#65002
0#
0+
#70002
1#
1+
#75002
0#
0+
#80002
1#
0$
1+
0,
#85002
0#
0+
#90002
1#
1&
b0000000000000101 (
b0000000000101010 *
1+
1.
b0000000000000101 0
b0000000000101010 2
#95002
0#
0+
#100002
1#
b0000000000000101 *
1+
b0000000000000101 2
b00000101 3
#105002
0#
0+
#110002
1#
0%
0&
b00000010 '
b0000000000001010 (
1+
0-
0.
b00000010 /
b0000000000001010 0
#115002
0#
0+
#120002
1#
b00000010 )
b0000000000010100 *
1+
b00000010 1
b0000000000010100 2
#125002
0#
0+
#130002
1#
1+
#130003
1$
b00000000 )
b0000000000000000 *
1,
b00000000 1
b0000000000000000 2
b00000000 3
#135003
0#
0+
#140003
1#
1+
#145003
0#
0+
#150003
1#
0$
1+
0,
#155003
0#
0+
#160003
1#
1%
1&
b0000000000000111 (
b00000010 )
b0000000000001010 *
1+
1-
1.
b0000000000000111 0
b00000010 1
b0000000000001010 2
#165003
0#
0+
#170003
1#
b00000000 )
b0000000000000111 *
1+
b00000000 1
b0000000000000111 2
b00000111 3
#175003
0#
0+
#180003
1#
0%
0&
b00000011 '
b0000000000000000 (
1+
0-
0.
b00000011 /
b0000000000000000 0
#185003
0#
0+
#190003
1#
b00000011 )
b0000000000010101 *
1+
b00000011 1
b0000000000010101 2
#195003
0#
0+
#200003
1#
b00000100 '
b0000000001100100 (
1+
b00000100 /
b0000000001100100 0
#205003
0#
0+
#210003
1#
b00000100 )
b0000000010000000 *
1+
b00000100 1
b0000000010000000 2
#215003
0#
0+
#220003
1#
1+
#220004
1$
b00000000 )
b0000000000000000 *
1,
b00000000 1
b0000000000000000 2
b00000000 3
#225004
0#
0+
#230004
1#
1+
#235004
0#
0+
#240004
1#
0$
1+
0,
#245004
0#
0+
#250004
1#
1%
1&
b0000000000000001 (
b00000100 )
b0000000001100100 *
1+
1-
1.
b0000000000000001 0
b00000100 1
b0000000001100100 2
#255004
0#
0+
#260004
1#
b00000000 )
b0000000000000001 *
1+
b00000000 1
b0000000000000001 2
b00000001 3
#265004
0#
0+
#270004
1#
0%
0&
b01100011 '
b0000000000000000 (
1+
0-
0.
b01100011 /
b0000000000000000 0
#275004
0#
0+
#280004
1#
b01100011 )
b0000000001100011 *
1+
b01100011 1
b0000000001100011 2
#285004
0#
0+
#290004
1#
b00101010 '
1+
b00101010 /
#295004
0#
0+
#300004
1#
b00101010 )
b0000000000101010 *
1+
b00101010 1
b0000000000101010 2
