rtl/weight_fifo.sv
`timescale 1ns / 1ps

module weight_fifo (
    input  logic       clk,
    input  logic       rst,
    input  logic       push,       // From DDR controller
    input  logic       pop,        // From MMU controller (during en_load_weight)
    input  logic [7:0] data_in,
    output logic [7:0] data_out
);

    logic [7:0] buffer [4]; // Tiny depth (4 deep)
    logic [1:0] wr_ptr, rd_ptr;

    always_ff @(posedge clk or posedge rst) begin
        if (rst) begin
            wr_ptr <= 2'd0;
            rd_ptr <= 2'd0;
            data_out <= 8'd0;
        end else begin
            // Write (Push)
            if (push) begin
                buffer[wr_ptr] <= data_in;
                wr_ptr <= wr_ptr + 1'd1;
            end

            // Read (Pop) - Feeds the MMU Column
            if (pop) begin
                data_out <= buffer[rd_ptr];
                rd_ptr <= rd_ptr + 1'd1;
            end
        end
    end

endmodule

sim/waves/weight_fifo.vcd
$version Generated by VerilatedVcd $end
$timescale 1ps $end
 $scope module $rootio $end
  $var wire 1 # clk $end
  $var wire 1 $ rst $end
  $var wire 1 % push $end
  $var wire 1 & pop $end
  $var wire 8 ' data_in [7:0] $end
  $var wire 8 ( data_out [7:0] $end
 $upscope $end
 $scope module weight_fifo $end
  $var wire 1 ) clk $end
  $var wire 1 * rst $end
  $var wire 1 + push $end
  $var wire 1 , pop $end
  $var wire 8 - data_in [7:0] $end
  $var wire 8 . data_out [7:0] $end
  $var wire 8 / buffer[0] [7:0] $end
  $var wire 8 0 buffer[1] [7:0] $end
  $var wire 8 1 buffer[2] [7:0] $end
  $var wire 8 2 buffer[3] [7:0] $end
  $var wire 2 3 wr_ptr [1:0] $end
  $var wire 2 4 rd_ptr [1:0] $end
 $upscope $end
$enddefinitions $end


#0
1#
1$
0%
0&
b00000000 '
b00000000 (
1)
1*
0+
0,
b00000000 -
b00000000 .
b00000000 /
b00000000 0
b00000000 1
b00000000 2
b00 3
b00 4
#5000
0#
0)
#10000
1#
1)
#15001
0#
0)
#20001
1#
1)
#25001
0#
0)
#30001
1#
0$
1)
0*
#35001
0#
0)
#40001
1#
1%
b00001010 '
1)
1+
b00001010 -
#45001
0#
0)
#50001
1#
b00010100 '
1)
b00010100 -
b00001010 /
b01 3
#55001
0#
0)
#60001
1#
b00011110 '
1)
b00011110 -
b00010100 0
b10 3
#65001
0#
0)
#70001
1#
b00101000 '
1)
b00101000 -
b00011110 1
b11 3
#75001
0#
0)
#80001
1#
0%
b00000000 '
1)
0+
b00000000 -
b00101000 2
b00 3
#85001
0#
0)
#90001
1#
1&
1)
1,
#95001
0#
0)
#100001
1#
b00001010 (
1)
b00001010 .
b01 4
#105001
0#
0)
#110001
1#
b00010100 (
1)
b00010100 .
b10 4
#115001
0#
0)
#120001
1#
b00011110 (
1)
b00011110 .
b11 4
#125001
0#
0)
#130001
1#
b00101000 (
1)
b00101000 .
b00 4
#135001
0#
0&
0)
0,
#140001
1#
1)
#140002
1$
b00000000 (
1*
b00000000 .
#145002
0#
0)
#150002
1#
1)
#155002
0#
0)
#160002
1#
0$
1)
0*
#165002
0#
0)
#170002
1#
1%
1)
1+
#175002
0#
0)
#180002
1#
b00000001 '
1)
b00000001 -
b00000000 /
b01 3
#185002
0#
0)
#190002
1#
b00000010 '
1)
b00000010 -
b00000001 0
b10 3
#195002
0#
0)
#200002
1#
b00000011 '
1)
b00000011 -
b00000010 1
b11 3
#205002
0#
0)
#210002
1#
0%
b00000000 '
1)
0+
b00000000 -
b00000011 2
b00 3
#215002
0#
0)
#220002
1#
1&
1)
1,
#225002
0#
0)
#230002
1#
1)
b01 4
#235002
0#
0)
#240002
1#
b00000001 (
1)
b00000001 .
b10 4
#245002
0#
0)
#250002
1#
b00000010 (
1)
b00000010 .
b11 4
#255002
0#
0)
#260002
1#
b00000011 (
1)
b00000011 .
b00 4
#265002
0#
0&
0)
0,
#270002
1#
1%
b00001010 '
1)
1+
b00001010 -
#275002
0#
0)
#280002
1#
b00001011 '
1)
b00001011 -
b00001010 /
b01 3
#285002
0#
0)
#290002
1#
b00001100 '
1)
b00001100 -
b00001011 0
b10 3
#295002
0#
0)
#300002
1#
b00001101 '
1)
b00001101 -
b00001100 1
b11 3
#305002
0#
0)
#310002
1#
0%
b00000000 '
1)
0+
b00000000 -
b00001101 2
b00 3
#315002
0#
0)
#320002
1#
1&
1)
1,
#325002
0#
0)
#330002
1#
b00001010 (
1)
b00001010 .
b01 4
#335002
0#
0)
#340002
1#
b00001011 (
1)
b00001011 .
b10 4
#345002
0#
0)
#350002
1#
b00001100 (
1)
b00001100 .
b11 4
#355002
0#
0)
#360002
1#
b00001101 (
1)
b00001101 .
b00 4
#365002
0#
0&
0)
0,
